certgrinderd/__init__.py
certgrinderd/certgrinderd.conf.dist
certgrinderd/certgrinderd.py
certgrinderd/manual-auth-hook.sh
certgrinderd/manual-cleanup-hook.sh
certgrinderd/tests/__init__.py
certgrinderd/tests/test_certgrinderd.py
certgrinderd-0.21.0.dist-info/licenses/LICENSE
certgrinderd-0.21.0.dist-info/METADATA
certgrinderd-0.21.0.dist-info/WHEEL
certgrinderd-0.21.0.dist-info/entry_points.txt
certgrinderd-0.21.0.dist-info/top_level.txt
certgrinderd-0.21.0.dist-info/RECORD
